{
  "railway": {
    "projectId": "ad62f340-fcfd-4989-b5bb-18753b28d8c8",
    "projectName": "AI Photo Studio WhatsApp",
    "environment": "production",
    "environmentId": "13228f5e-8af5-4f5e-b57e-b1dfccd567ec",
    "service": "api",
    "requiredServices": [
      "api",
      "postgres",
      "redis"
    ]
  },
  "cloudflare": {
    "accountId": "85f6a6181b4653c2a45e69cb7ce8a474",
    "r2BucketName": "ai-photo-studio-whatsapp-r2",
    "publicBaseUrl": "https://85f6a6181b4653c2a45e69cb7ce8a474.r2.cloudflarestorage.com"
  },
  "git": {
    "remote": "https://github.com/gardenshop/ai-photo-studio-whatsapp.git",
    "branch": "main"
  }
}
