{
  "image_name": "Untitled design (11).png",
  "timestamp": "2026-07-13T11:42:27.856615",
  "stages": {
    "original": "diagnostics\\run_20260713_114212\\white_products_Untitled design (11)\\original.png",
    "preprocessed_input": "diagnostics\\run_20260713_114212\\white_products_Untitled design (11)\\original.png",
    "raw_logits": null,
    "raw_mask": "diagnostics\\run_20260713_114212\\white_products_Untitled design (11)\\alpha.png",
    "candidate_masks": "diagnostics\\run_20260713_114212\\white_products_Untitled design (11)\\alpha.png",
    "chosen_mask": "diagnostics\\run_20260713_114212\\white_products_Untitled design (11)\\alpha.png",
    "refined_mask": "diagnostics\\run_20260713_114212\\white_products_Untitled design (11)\\alpha.png",
    "alpha": "diagnostics\\run_20260713_114212\\white_products_Untitled design (11)\\alpha.png",
    "foreground": "diagnostics\\run_20260713_114212\\white_products_Untitled design (11)\\foreground.png",
    "rgba": "diagnostics\\run_20260713_114212\\white_products_Untitled design (11)\\returned_png.png",
    "returned_png": "diagnostics\\run_20260713_114212\\white_products_Untitled design (11)\\returned_png.png",
    "browser_png": "diagnostics\\run_20260713_114212\\white_products_Untitled design (11)\\browser_png.png",
    "overlay_mask": "diagnostics\\run_20260713_114212\\white_products_Untitled design (11)\\overlay_mask.png"
  },
  "provider": "rembg-u2netp",
  "model": "u2netp",
  "iqs": {
    "foreground_coverage": 0.06405092592592593,
    "edge_continuity": 0.0,
    "connected_components": 1,
    "largest_component_pct": 1.0,
    "alpha_entropy": 0.22990711172914008,
    "bg_leakage": 0.19438700274348422,
    "mask_confidence": 0.9920961934156378,
    "mask_smoothness": 0.9983562231063843,
    "boundary_f1": 0.33587653428636444,
    "rgba_integrity": 0.5,
    "iqs": 26.553605943499225
  },
  "sha256": "fcf7aaa2a873288186ef413d14bc26167158cab47dc1c268b62b1158537a214e",
  "status": "FAIL"
}